hey_babe/__init__.py
hey_babe/cli.py
hey_babe/hey_babe.py
hey_babe_ahsan.freedi-0.1.0.dist-info/AUTHORS.rst
hey_babe_ahsan.freedi-0.1.0.dist-info/LICENSE
hey_babe_ahsan.freedi-0.1.0.dist-info/METADATA
hey_babe_ahsan.freedi-0.1.0.dist-info/WHEEL
hey_babe_ahsan.freedi-0.1.0.dist-info/entry_points.txt
hey_babe_ahsan.freedi-0.1.0.dist-info/top_level.txt
hey_babe_ahsan.freedi-0.1.0.dist-info/RECORD
