Metadata-Version: 2.1
Name: hey-babe-ahsan.freedi
Version: 0.1.0
Summary: test
Home-page: https://github.com/ashan.aslam/hey_babe
Author: ahsan aslam
Author-email: ahsanaslamfreedi@gmail.com
License: MIT license
Keywords: hey_babe
Platform: UNKNOWN
Classifier: Development Status :: 2 - Pre-Alpha
Classifier: Intended Audience :: Developers
Classifier: License :: OSI Approved :: MIT License
Classifier: Natural Language :: English
Classifier: Programming Language :: Python :: 3
Classifier: Programming Language :: Python :: 3.5
Classifier: Programming Language :: Python :: 3.6
Classifier: Programming Language :: Python :: 3.7
Classifier: Programming Language :: Python :: 3.8
Requires-Python: >=3.5
Requires-Dist: Click (>=7.0)
